vista/__init__.py
vista/cli.py
vista/vista.py
vista-0.1.0.dist-info/LICENSE
vista-0.1.0.dist-info/METADATA
vista-0.1.0.dist-info/WHEEL
vista-0.1.0.dist-info/top_level.txt
vista-0.1.0.dist-info/RECORD
