Metadata-Version: 2.1
Name: vista
Version: 0.1.0
Summary: Data-driven simulation for training and evaluating full-scale autonomous vehicles
Home-page: https://github.com/aamini/vista
Author: Alexander Amini
Author-email: amini@mit.edu
License: MIT license
Keywords: vista
Platform: UNKNOWN
Classifier: Development Status :: 2 - Pre-Alpha
Classifier: Intended Audience :: Developers
Classifier: License :: OSI Approved :: MIT License
Classifier: Natural Language :: English
Classifier: Programming Language :: Python :: 3
Classifier: Programming Language :: Python :: 3.5
Classifier: Programming Language :: Python :: 3.6
Classifier: Programming Language :: Python :: 3.7
Classifier: Programming Language :: Python :: 3.8
Requires-Python: >=3.5
